LICENSE
README.md
setup.py
bin/scripts/vilmedic-download
bin/scripts/vilmedic-metrics
vilmedic/__init__.py
vilmedic/constants.py
vilmedic.egg-info/PKG-INFO
vilmedic.egg-info/SOURCES.txt
vilmedic.egg-info/dependency_links.txt
vilmedic.egg-info/not-zip-safe
vilmedic.egg-info/requires.txt
vilmedic.egg-info/top_level.txt
vilmedic/blocks/__init__.py
vilmedic/blocks/classifier/__init__.py
vilmedic/blocks/classifier/classifier.py
vilmedic/blocks/classifier/evaluation.py
vilmedic/blocks/huggingface/__init__.py
vilmedic/blocks/huggingface/decoder/__init__.py
vilmedic/blocks/huggingface/decoder/beam_search.py
vilmedic/blocks/huggingface/decoder/decoder_model.py
vilmedic/blocks/huggingface/decoder/evaluation.py
vilmedic/blocks/huggingface/decoder/evaluation_force.py
vilmedic/blocks/huggingface/encoder/__init__.py
vilmedic/blocks/huggingface/encoder/encoder_model.py
vilmedic/blocks/huggingface/encoder_decoder/__init__.py
vilmedic/blocks/huggingface/encoder_decoder/encoder_decoder_model.py
vilmedic/blocks/huggingface/encoder_decoder/evaluation.py
vilmedic/blocks/losses/__init__.py
vilmedic/blocks/losses/mvqa/LabelSmoothingCrossEntropyLoss.py
vilmedic/blocks/losses/mvqa/__init__.py
vilmedic/blocks/losses/selfsup/ConVIRTLoss.py
vilmedic/blocks/losses/selfsup/GLoRIALoss.py
vilmedic/blocks/losses/selfsup/InfoNCELoss.py
vilmedic/blocks/losses/selfsup/VICREGLoss.py
vilmedic/blocks/losses/selfsup/__init__.py
vilmedic/blocks/rl/SCST.py
vilmedic/blocks/rl/__init__.py
vilmedic/blocks/schedulers/DecreasingCosineAnnealingWarmRestarts.py
vilmedic/blocks/schedulers/LinearWarmupCosineAnnealingLR.py
vilmedic/blocks/schedulers/__init__.py
vilmedic/blocks/scorers/__init__.py
vilmedic/blocks/scorers/post_processing.py
vilmedic/blocks/scorers/scores.py
vilmedic/blocks/scorers/utils.py
vilmedic/blocks/scorers/NLG/__init__.py
vilmedic/blocks/scorers/NLG/bertscore/__init__.py
vilmedic/blocks/scorers/NLG/bertscore/bertscore.py
vilmedic/blocks/scorers/NLG/bleu/__init__.py
vilmedic/blocks/scorers/NLG/bleu/bleu.py
vilmedic/blocks/scorers/NLG/bleu/bleu_scorer.py
vilmedic/blocks/scorers/NLG/ciderD/__init__.py
vilmedic/blocks/scorers/NLG/ciderD/ciderD.py
